statuspage_agent/__init__.py
statuspage_agent/agent.py
statuspage_agent-0.2.0.dist-info/METADATA
statuspage_agent-0.2.0.dist-info/RECORD
statuspage_agent-0.2.0.dist-info/WHEEL
statuspage_agent-0.2.0.dist-info/top_level.txt
